pyelox/__init__.py
pyelox/core.py
pyelox/db.py
pyelox/env.py
pyelox/request.py
pyelox/router.py
pyelox/security.py
pyelox/server.py
pyelox/sql.py
pyelox/static_handler.py
pyelox/template.py
pyelox-0.1.0.dist-info/METADATA
pyelox-0.1.0.dist-info/WHEEL
pyelox-0.1.0.dist-info/top_level.txt
pyelox-0.1.0.dist-info/RECORD
