Metadata-Version: 2.4
Name: pyelox
Version: 0.1.0
Summary: A minimalist, secure, and compact Python web framework.
Author: GuestRoblox Studios
Author-email: maria.gomes23.1949@gmail.com
Keywords: web framework,python,minimalist,micro-framework,secure,security,http,socket,low-level,high-performance,compact,routing,templating,wsgi,asgi,server,pyelox,API,Rest,development,app,fast,reliable,lightweight,production,async,concurrency,scalable,router,middleware,security-focused,easy-to-use,utility,library,web-development,backend
Classifier: Development Status :: 5 - Production/Stable
Classifier: Intended Audience :: Developers
Classifier: Intended Audience :: Education
Classifier: Intended Audience :: Information Technology
Classifier: Intended Audience :: System Administrators
Classifier: Intended Audience :: Science/Research
Classifier: Topic :: Internet
Classifier: Topic :: Internet :: WWW/HTTP
Classifier: Topic :: Internet :: WWW/HTTP :: Dynamic Content
Classifier: Topic :: Internet :: WWW/HTTP :: WSGI
Classifier: Topic :: Software Development
Classifier: Topic :: Software Development :: Libraries
Classifier: Topic :: Software Development :: Libraries :: Python Modules
Classifier: Topic :: Software Development :: Libraries :: Application Frameworks
Classifier: Topic :: Utilities
Classifier: Topic :: System :: Networking
Classifier: Topic :: Security
Classifier: Environment :: Web Environment
Classifier: License :: OSI Approved :: MIT License
Classifier: Programming Language :: Python :: 3
Classifier: Programming Language :: Python :: 3.8
Classifier: Programming Language :: Python :: 3.9
Classifier: Programming Language :: Python :: 3.10
Classifier: Programming Language :: Python :: 3.11
Classifier: Programming Language :: Python :: 3.12
Classifier: Programming Language :: Python :: Implementation :: CPython
Classifier: Operating System :: OS Independent
Classifier: Operating System :: POSIX :: Linux
Classifier: Operating System :: Microsoft :: Windows
Classifier: Operating System :: MacOS
Requires-Python: >=3.8
Requires-Dist: python-dotenv
Dynamic: author
Dynamic: author-email
Dynamic: classifier
Dynamic: description
Dynamic: description-content-type
Dynamic: keywords
Dynamic: requires-dist
Dynamic: requires-python
Dynamic: summary
